littlecms/__init__.py
littlecms/admin.py
littlecms/apps.py
littlecms/context_processors.py
littlecms/models.py
littlecms/tests.py
littlecms/urls.py
littlecms/views.py
littlecms/migrations/0001_initial.py
littlecms/migrations/__init__.py
littlecms/static/__init__.py
littlecms/static/css/__init__.py
littlecms/static/css/simplecms.css
littlecms/static/js/__init__.py
littlecms/static/js/simplecms.js
littlecms/templates/__init__.py
littlecms/templates/littlecms/__init__.py
littlecms/templates/littlecms/article_detail.html
littlecms/templates/littlecms/base.html
littlecms/templates/littlecms/basic.html
littlecms/templates/littlecms/bootstrap.html
littlecms/templates/littlecms/breadcrumb_item.html
littlecms/templates/littlecms/card.html
littlecms/templates/littlecms/card_slide.html
littlecms/templates/littlecms/card_slide_captions.html
littlecms/templates/littlecms/card_slide_captions_controls.html
littlecms/templates/littlecms/card_slide_controls.html
littlecms/templates/littlecms/content.html
littlecms/templates/littlecms/menu.html
littlecms/templates/littlecms/menu_root_item.html
littlecms/templates/littlecms/menu_sub_item.html
littlecms/templates/littlecms/page_header.html
django_little_cms-0.0.2.dist-info/METADATA
django_little_cms-0.0.2.dist-info/WHEEL
django_little_cms-0.0.2.dist-info/top_level.txt
django_little_cms-0.0.2.dist-info/RECORD
