Metadata-Version: 2.1
Name: django-little-cms
Version: 0.0.2
Summary: CMS sencillo para admin de django
Home-page: https://github.com/rafaga2469
Author: Rafael Ricardo Pinto
Author-email: rafaga2469@gmail.com
License: MIT
Platform: UNKNOWN
Requires-Dist: Django (>=4.0.6)
Requires-Dist: django-bootstrap5 (>=21.3)
Requires-Dist: django-ckeditor (>=6.4.2)
Requires-Dist: django-colorfield (>=0.7.2)
